mux2to1.v
// 2 : 1 Multiplexer Module

module mux2to1(input A, B, S, output Y);
    wire S_not, A_and, B_and;

    // Gates for the structural model
    not (S_not, S);        // S_not = ~S
    and (A_and, A, S_not), (B_and, B, S); // A_and = A & ~S , B_and = B & S
    or (Y, A_and, B_and);  // Y = A_and | B_and
endmodule

mux2to1_tb.v
/* Test_bench for 2to1mux
saved in file 2to1mux_tb.v*/

`include "mux2to1.v" // The include directive is used to include the contents of one file into another during preprocessing.


module mux2to1_tb;
    reg A, B, S; // Declare inputs as reg
    wire Y;      // Declare output as wire

    // Instantiating the MUX module
    mux2to1 mux1(A, B, S, Y);

    initial begin

        $dumpfile("mux2to1.vcd"); // vcd - value change dump
        $dumpvars(0,mux2to1_tb);

        // Display header
        $display("Time | A B S | Y");
        $display("----------------");

        // Apply test cases
        A = 0; B = 0; S = 0; #1; $display("%4d | %b %b %b | %b", $time, A, B, S, Y);
        A = 0; B = 1; S = 0; #1; $display("%4d | %b %b %b | %b", $time, A, B, S, Y);
        A = 1; B = 0; S = 0; #1; $display("%4d | %b %b %b | %b", $time, A, B, S, Y);
        A = 1; B = 1; S = 0; #1; $display("%4d | %b %b %b | %b", $time, A, B, S, Y);

        A = 0; B = 0; S = 1; #1; $display("%4d | %b %b %b | %b", $time, A, B, S, Y);
        A = 0; B = 1; S = 1; #1; $display("%4d | %b %b %b | %b", $time, A, B, S, Y);
        A = 1; B = 0; S = 1; #1; $display("%4d | %b %b %b | %b", $time, A, B, S, Y);
        A = 1; B = 1; S = 1; #1; $display("%4d | %b %b %b | %b", $time, A, B, S, Y);

        $finish; // End the simulation
    end
endmodule

mux2to1.vcd
$date
	Fri Jan 03 15:43:09 2025
$end
$version
	Icarus Verilog
$end
$timescale
	1s
$end
$scope module mux2to1_tb $end
$var wire 1 ! Y $end
$var reg 1 " A $end
$var reg 1 # B $end
$var reg 1 $ S $end
$scope module mux1 $end
$var wire 1 " A $end
$var wire 1 % A_and $end
$var wire 1 # B $end
$var wire 1 & B_and $end
$var wire 1 $ S $end
$var wire 1 ' S_not $end
$var wire 1 ! Y $end
$upscope $end
$upscope $end
$enddefinitions $end
$comment Show the parameter values. $end
$dumpall
$end
#0
$dumpvars
1'
0&
0%
0$
0#
0"
0!
$end
#1
1#
#2
1!
1%
0#
1"
#3
1#
#4
0!
0'
0%
1$
0#
0"
#5
1!
1&
1#
#6
0!
0&
0#
1"
#7
1!
1&
1#
